{
  "order1": [
    {
      "data": {
        "id": 1,
        "userName": "kim",
        "productName": "product",
        "quantity": 329.0,
        "createdAt": "2025-04-09T07:12:34.117538Z",
        "updatedAt": "2025-04-09T07:17:37.768969Z"
      },
      "diffSec": 303
    }
  ],
  "order2": [
    {
      "data": {
        "id": 1,
        "userName": "kim",
        "productName": "product",
        "quantity": 3001.0,
        "createdAt": "2025-04-09T07:30:09.206808Z",
        "updatedAt": "2025-04-09T07:36:33.952635Z"
      },
      "diffSec": 384
    }
  ],
  "order3": [
    {
      "data": {
        "id": 1,
        "userName": "kim",
        "productName": "product",
        "quantity": 3001.0,
        "createdAt": "2025-04-09T07:36:53.671779Z",
        "updatedAt": "2025-04-09T07:42:26.952778Z"
      },
      "diffSec": 333
    }
  ]
}